aio_sockets/__init__.py
aio_sockets/aio_sockets.py
aio_sockets-0.1.0.dist-info/licenses/LICENSE
aio_sockets-0.1.0.dist-info/METADATA
aio_sockets-0.1.0.dist-info/WHEEL
aio_sockets-0.1.0.dist-info/top_level.txt
aio_sockets-0.1.0.dist-info/RECORD
