Metadata-Version: 2.4
Name: aio_sockets
Version: 0.1.0
Summary: Simplified Async TCP and UDP Sockets for Python 3.8+
Author-email: yinkaisheng <yinkaisheng@foxmail.com>
License: Apache-2.0
Project-URL: Homepage, https://github.com/yinkaisheng/aio-sockets
Keywords: asyncio,socket,networking
Classifier: Programming Language :: Python :: 3
Classifier: License :: OSI Approved :: Apache Software License
Classifier: Operating System :: OS Independent
Requires-Python: >=3.8
License-File: LICENSE
Dynamic: license-file
